<?xml version="1.0" encoding="UTF-8"?>
<routes xmlns:xsi="http://www.w3.org/2001/XMLSchema-instance" xsi:noNamespaceSchemaLocation="http://sumo.dlr.de/xsd/routes_file.xsd">
  <flow id="JF4560" begin="0" fromJunction="J11" toJunction="J15" end="3600" vehsPerHour="305.33333333333337"/>
  <flow id="JF4561" begin="0" fromJunction="J11" toJunction="J16" end="3600" vehsPerHour="76.33333333333334"/>
  <flow id="JF4562" begin="0" fromJunction="J11" toJunction="J17" end="3600" vehsPerHour="76.33333333333334"/>
  <flow id="JF4563" begin="0" fromJunction="J11" toJunction="J18" end="3600" vehsPerHour="76.33333333333334"/>
  <flow id="JF4564" begin="0" fromJunction="J11" toJunction="J19" end="3600" vehsPerHour="76.33333333333334"/>
  <flow id="JF4565" begin="0" fromJunction="J11" toJunction="J20" end="3600" vehsPerHour="76.33333333333334"/>
  <flow id="JF4566" begin="0" fromJunction="J11" toJunction="J21" end="3600" vehsPerHour="76.33333333333334"/>
  <flow id="JF4567" begin="0" fromJunction="J11" toJunction="J22" end="3600" vehsPerHour="76.33333333333334"/>
  <flow id="JF4568" begin="0" fromJunction="J11" toJunction="J7" end="3600" vehsPerHour="76.33333333333334"/>
  <flow id="JF4569" begin="0" fromJunction="J11" toJunction="J8" end="3600" vehsPerHour="76.33333333333334"/>
  <flow id="JF4570" begin="0" fromJunction="J11" toJunction="J9" end="3600" vehsPerHour="76.33333333333334"/>
  <flow id="JF4571" begin="0" fromJunction="J11" toJunction="J14" end="3600" vehsPerHour="76.33333333333334"/>
  <flow id="JF4572" begin="0" fromJunction="J11" toJunction="J13" end="3600" vehsPerHour="76.33333333333334"/>
  <flow id="JF4573" begin="0" fromJunction="J11" toJunction="J12" end="3600" vehsPerHour="76.33333333333334"/>
  <flow id="JF4574" begin="0" fromJunction="J11" toJunction="J10" end="3600" vehsPerHour="76.33333333333334"/>
  <flow id="JF4575" begin="0" fromJunction="J12" toJunction="J10" end="3600" vehsPerHour="18.32"/>
  <flow id="JF4576" begin="0" fromJunction="J12" toJunction="J11" end="3600" vehsPerHour="18.32"/>
  <flow id="JF4577" begin="0" fromJunction="J12" toJunction="J13" end="3600" vehsPerHour="18.32"/>
  <flow id="JF4578" begin="0" fromJunction="J12" toJunction="J14" end="3600" vehsPerHour="18.32"/>
  <flow id="JF4579" begin="0" fromJunction="J12" toJunction="J15" end="3600" vehsPerHour="18.32"/>
  <flow id="JF4580" begin="0" fromJunction="J12" toJunction="J16" end="3600" vehsPerHour="18.32"/>
  <flow id="JF4581" begin="0" fromJunction="J12" toJunction="J17" end="3600" vehsPerHour="18.32"/>
  <flow id="JF4582" begin="0" fromJunction="J12" toJunction="J18" end="3600" vehsPerHour="18.32"/>
  <flow id="JF4583" begin="0" fromJunction="J12" toJunction="J19" end="3600" vehsPerHour="18.32"/>
  <flow id="JF4584" begin="0" fromJunction="J12" toJunction="J20" end="3600" vehsPerHour="18.32"/>
  <flow id="JF4585" begin="0" fromJunction="J12" toJunction="J21" end="3600" vehsPerHour="18.32"/>
  <flow id="JF4586" begin="0" fromJunction="J12" toJunction="J22" end="3600" vehsPerHour="18.32"/>
  <flow id="JF4587" begin="0" fromJunction="J12" toJunction="J7" end="3600" vehsPerHour="18.32"/>
  <flow id="JF4588" begin="0" fromJunction="J12" toJunction="J8" end="3600" vehsPerHour="18.32"/>
  <flow id="JF4589" begin="0" fromJunction="J12" toJunction="J9" end="3600" vehsPerHour="18.32"/>
  <flow id="JF4590" begin="0" fromJunction="J13" toJunction="J10" end="3600" vehsPerHour="18.32"/>
  <flow id="JF4591" begin="0" fromJunction="J13" toJunction="J11" end="3600" vehsPerHour="18.32"/>
  <flow id="JF4592" begin="0" fromJunction="J13" toJunction="J12" end="3600" vehsPerHour="18.32"/>
  <flow id="JF4593" begin="0" fromJunction="J13" toJunction="J14" end="3600" vehsPerHour="18.32"/>
  <flow id="JF4594" begin="0" fromJunction="J13" toJunction="J15" end="3600" vehsPerHour="18.32"/>
  <flow id="JF4595" begin="0" fromJunction="J13" toJunction="J16" end="3600" vehsPerHour="18.32"/>
  <flow id="JF4596" begin="0" fromJunction="J13" toJunction="J17" end="3600" vehsPerHour="18.32"/>
  <flow id="JF4597" begin="0" fromJunction="J13" toJunction="J18" end="3600" vehsPerHour="18.32"/>
  <flow id="JF4598" begin="0" fromJunction="J13" toJunction="J19" end="3600" vehsPerHour="18.32"/>
  <flow id="JF4599" begin="0" fromJunction="J13" toJunction="J20" end="3600" vehsPerHour="18.32"/>
  <flow id="JF4600" begin="0" fromJunction="J13" toJunction="J21" end="3600" vehsPerHour="18.32"/>
  <flow id="JF4601" begin="0" fromJunction="J13" toJunction="J22" end="3600" vehsPerHour="18.32"/>
  <flow id="JF4602" begin="0" fromJunction="J13" toJunction="J7" end="3600" vehsPerHour="18.32"/>
  <flow id="JF4603" begin="0" fromJunction="J13" toJunction="J8" end="3600" vehsPerHour="18.32"/>
  <flow id="JF4604" begin="0" fromJunction="J13" toJunction="J9" end="3600" vehsPerHour="18.32"/>
  <flow id="JF4605" begin="0" fromJunction="J14" toJunction="J10" end="3600" vehsPerHour="18.32"/>
  <flow id="JF4606" begin="0" fromJunction="J14" toJunction="J11" end="3600" vehsPerHour="18.32"/>
  <flow id="JF4607" begin="0" fromJunction="J14" toJunction="J12" end="3600" vehsPerHour="18.32"/>
  <flow id="JF4608" begin="0" fromJunction="J14" toJunction="J13" end="3600" vehsPerHour="18.32"/>
  <flow id="JF4609" begin="0" fromJunction="J14" toJunction="J15" end="3600" vehsPerHour="18.32"/>
  <flow id="JF4610" begin="0" fromJunction="J14" toJunction="J16" end="3600" vehsPerHour="18.32"/>
  <flow id="JF4611" begin="0" fromJunction="J14" toJunction="J17" end="3600" vehsPerHour="18.32"/>
  <flow id="JF4612" begin="0" fromJunction="J14" toJunction="J18" end="3600" vehsPerHour="18.32"/>
  <flow id="JF4613" begin="0" fromJunction="J14" toJunction="J19" end="3600" vehsPerHour="18.32"/>
  <flow id="JF4614" begin="0" fromJunction="J14" toJunction="J20" end="3600" vehsPerHour="18.32"/>
  <flow id="JF4615" begin="0" fromJunction="J14" toJunction="J21" end="3600" vehsPerHour="18.32"/>
  <flow id="JF4616" begin="0" fromJunction="J14" toJunction="J22" end="3600" vehsPerHour="18.32"/>
  <flow id="JF4617" begin="0" fromJunction="J14" toJunction="J7" end="3600" vehsPerHour="18.32"/>
  <flow id="JF4618" begin="0" fromJunction="J14" toJunction="J8" end="3600" vehsPerHour="18.32"/>
  <flow id="JF4619" begin="0" fromJunction="J14" toJunction="J9" end="3600" vehsPerHour="18.32"/>
  <flow id="JF4620" begin="0" fromJunction="J15" toJunction="J10" end="3600" vehsPerHour="18.32"/>
  <flow id="JF4621" begin="0" fromJunction="J15" toJunction="J11" end="3600" vehsPerHour="18.32"/>
  <flow id="JF4622" begin="0" fromJunction="J15" toJunction="J12" end="3600" vehsPerHour="18.32"/>
  <flow id="JF4623" begin="0" fromJunction="J15" toJunction="J13" end="3600" vehsPerHour="18.32"/>
  <flow id="JF4624" begin="0" fromJunction="J15" toJunction="J14" end="3600" vehsPerHour="18.32"/>
  <flow id="JF4625" begin="0" fromJunction="J15" toJunction="J16" end="3600" vehsPerHour="18.32"/>
  <flow id="JF4626" begin="0" fromJunction="J15" toJunction="J17" end="3600" vehsPerHour="18.32"/>
  <flow id="JF4627" begin="0" fromJunction="J15" toJunction="J18" end="3600" vehsPerHour="18.32"/>
  <flow id="JF4628" begin="0" fromJunction="J15" toJunction="J19" end="3600" vehsPerHour="18.32"/>
  <flow id="JF4629" begin="0" fromJunction="J15" toJunction="J20" end="3600" vehsPerHour="18.32"/>
  <flow id="JF4630" begin="0" fromJunction="J15" toJunction="J21" end="3600" vehsPerHour="18.32"/>
  <flow id="JF4631" begin="0" fromJunction="J15" toJunction="J22" end="3600" vehsPerHour="18.32"/>
  <flow id="JF4632" begin="0" fromJunction="J15" toJunction="J7" end="3600" vehsPerHour="18.32"/>
  <flow id="JF4633" begin="0" fromJunction="J15" toJunction="J8" end="3600" vehsPerHour="18.32"/>
  <flow id="JF4634" begin="0" fromJunction="J15" toJunction="J9" end="3600" vehsPerHour="18.32"/>
  <flow id="JF4635" begin="0" fromJunction="J16" toJunction="J10" end="3600" vehsPerHour="18.32"/>
  <flow id="JF4636" begin="0" fromJunction="J16" toJunction="J11" end="3600" vehsPerHour="18.32"/>
  <flow id="JF4637" begin="0" fromJunction="J16" toJunction="J12" end="3600" vehsPerHour="18.32"/>
  <flow id="JF4638" begin="0" fromJunction="J16" toJunction="J13" end="3600" vehsPerHour="18.32"/>
  <flow id="JF4639" begin="0" fromJunction="J16" toJunction="J14" end="3600" vehsPerHour="18.32"/>
  <flow id="JF4640" begin="0" fromJunction="J16" toJunction="J15" end="3600" vehsPerHour="18.32"/>
  <flow id="JF4641" begin="0" fromJunction="J16" toJunction="J17" end="3600" vehsPerHour="18.32"/>
  <flow id="JF4642" begin="0" fromJunction="J16" toJunction="J18" end="3600" vehsPerHour="18.32"/>
  <flow id="JF4643" begin="0" fromJunction="J16" toJunction="J19" end="3600" vehsPerHour="18.32"/>
  <flow id="JF4644" begin="0" fromJunction="J16" toJunction="J20" end="3600" vehsPerHour="18.32"/>
  <flow id="JF4645" begin="0" fromJunction="J16" toJunction="J21" end="3600" vehsPerHour="18.32"/>
  <flow id="JF4646" begin="0" fromJunction="J16" toJunction="J22" end="3600" vehsPerHour="18.32"/>
  <flow id="JF4647" begin="0" fromJunction="J16" toJunction="J7" end="3600" vehsPerHour="18.32"/>
  <flow id="JF4648" begin="0" fromJunction="J16" toJunction="J8" end="3600" vehsPerHour="18.32"/>
  <flow id="JF4649" begin="0" fromJunction="J16" toJunction="J9" end="3600" vehsPerHour="18.32"/>
  <flow id="JF4650" begin="0" fromJunction="J17" toJunction="J10" end="3600" vehsPerHour="18.32"/>
  <flow id="JF4651" begin="0" fromJunction="J17" toJunction="J11" end="3600" vehsPerHour="18.32"/>
  <flow id="JF4652" begin="0" fromJunction="J17" toJunction="J12" end="3600" vehsPerHour="18.32"/>
  <flow id="JF4653" begin="0" fromJunction="J17" toJunction="J13" end="3600" vehsPerHour="18.32"/>
  <flow id="JF4654" begin="0" fromJunction="J17" toJunction="J14" end="3600" vehsPerHour="18.32"/>
  <flow id="JF4655" begin="0" fromJunction="J17" toJunction="J15" end="3600" vehsPerHour="18.32"/>
  <flow id="JF4656" begin="0" fromJunction="J17" toJunction="J16" end="3600" vehsPerHour="18.32"/>
  <flow id="JF4657" begin="0" fromJunction="J17" toJunction="J18" end="3600" vehsPerHour="18.32"/>
  <flow id="JF4658" begin="0" fromJunction="J17" toJunction="J19" end="3600" vehsPerHour="18.32"/>
  <flow id="JF4659" begin="0" fromJunction="J17" toJunction="J20" end="3600" vehsPerHour="18.32"/>
  <flow id="JF4660" begin="0" fromJunction="J17" toJunction="J21" end="3600" vehsPerHour="18.32"/>
  <flow id="JF4661" begin="0" fromJunction="J17" toJunction="J22" end="3600" vehsPerHour="18.32"/>
  <flow id="JF4662" begin="0" fromJunction="J17" toJunction="J7" end="3600" vehsPerHour="18.32"/>
  <flow id="JF4663" begin="0" fromJunction="J17" toJunction="J8" end="3600" vehsPerHour="18.32"/>
  <flow id="JF4664" begin="0" fromJunction="J17" toJunction="J9" end="3600" vehsPerHour="18.32"/>
  <flow id="JF4665" begin="0" fromJunction="J18" toJunction="J10" end="3600" vehsPerHour="18.32"/>
  <flow id="JF4666" begin="0" fromJunction="J18" toJunction="J11" end="3600" vehsPerHour="18.32"/>
  <flow id="JF4667" begin="0" fromJunction="J18" toJunction="J12" end="3600" vehsPerHour="18.32"/>
  <flow id="JF4668" begin="0" fromJunction="J18" toJunction="J13" end="3600" vehsPerHour="18.32"/>
  <flow id="JF4669" begin="0" fromJunction="J18" toJunction="J14" end="3600" vehsPerHour="18.32"/>
  <flow id="JF4670" begin="0" fromJunction="J18" toJunction="J15" end="3600" vehsPerHour="18.32"/>
  <flow id="JF4671" begin="0" fromJunction="J18" toJunction="J16" end="3600" vehsPerHour="18.32"/>
  <flow id="JF4672" begin="0" fromJunction="J18" toJunction="J17" end="3600" vehsPerHour="18.32"/>
  <flow id="JF4673" begin="0" fromJunction="J18" toJunction="J19" end="3600" vehsPerHour="18.32"/>
  <flow id="JF4674" begin="0" fromJunction="J18" toJunction="J20" end="3600" vehsPerHour="18.32"/>
  <flow id="JF4675" begin="0" fromJunction="J18" toJunction="J21" end="3600" vehsPerHour="18.32"/>
  <flow id="JF4676" begin="0" fromJunction="J18" toJunction="J22" end="3600" vehsPerHour="18.32"/>
  <flow id="JF4677" begin="0" fromJunction="J18" toJunction="J7" end="3600" vehsPerHour="18.32"/>
  <flow id="JF4678" begin="0" fromJunction="J18" toJunction="J8" end="3600" vehsPerHour="18.32"/>
  <flow id="JF4679" begin="0" fromJunction="J18" toJunction="J9" end="3600" vehsPerHour="18.32"/>
  <flow id="JF4680" begin="0" fromJunction="J19" toJunction="J10" end="3600" vehsPerHour="18.32"/>
  <flow id="JF4681" begin="0" fromJunction="J19" toJunction="J11" end="3600" vehsPerHour="18.32"/>
  <flow id="JF4682" begin="0" fromJunction="J19" toJunction="J12" end="3600" vehsPerHour="18.32"/>
  <flow id="JF4683" begin="0" fromJunction="J19" toJunction="J13" end="3600" vehsPerHour="18.32"/>
  <flow id="JF4684" begin="0" fromJunction="J19" toJunction="J14" end="3600" vehsPerHour="18.32"/>
  <flow id="JF4685" begin="0" fromJunction="J19" toJunction="J15" end="3600" vehsPerHour="18.32"/>
  <flow id="JF4686" begin="0" fromJunction="J19" toJunction="J16" end="3600" vehsPerHour="18.32"/>
  <flow id="JF4687" begin="0" fromJunction="J19" toJunction="J17" end="3600" vehsPerHour="18.32"/>
  <flow id="JF4688" begin="0" fromJunction="J19" toJunction="J18" end="3600" vehsPerHour="18.32"/>
  <flow id="JF4689" begin="0" fromJunction="J19" toJunction="J20" end="3600" vehsPerHour="18.32"/>
  <flow id="JF4690" begin="0" fromJunction="J19" toJunction="J21" end="3600" vehsPerHour="18.32"/>
  <flow id="JF4691" begin="0" fromJunction="J19" toJunction="J22" end="3600" vehsPerHour="18.32"/>
  <flow id="JF4692" begin="0" fromJunction="J19" toJunction="J7" end="3600" vehsPerHour="18.32"/>
  <flow id="JF4693" begin="0" fromJunction="J19" toJunction="J8" end="3600" vehsPerHour="18.32"/>
  <flow id="JF4694" begin="0" fromJunction="J19" toJunction="J9" end="3600" vehsPerHour="18.32"/>
  <flow id="JF4695" begin="0" fromJunction="J20" toJunction="J10" end="3600" vehsPerHour="18.32"/>
  <flow id="JF4696" begin="0" fromJunction="J20" toJunction="J11" end="3600" vehsPerHour="18.32"/>
  <flow id="JF4697" begin="0" fromJunction="J20" toJunction="J12" end="3600" vehsPerHour="18.32"/>
  <flow id="JF4698" begin="0" fromJunction="J20" toJunction="J13" end="3600" vehsPerHour="18.32"/>
  <flow id="JF4699" begin="0" fromJunction="J20" toJunction="J14" end="3600" vehsPerHour="18.32"/>
  <flow id="JF4700" begin="0" fromJunction="J20" toJunction="J15" end="3600" vehsPerHour="18.32"/>
  <flow id="JF4701" begin="0" fromJunction="J20" toJunction="J16" end="3600" vehsPerHour="18.32"/>
  <flow id="JF4702" begin="0" fromJunction="J20" toJunction="J17" end="3600" vehsPerHour="18.32"/>
  <flow id="JF4703" begin="0" fromJunction="J20" toJunction="J18" end="3600" vehsPerHour="18.32"/>
  <flow id="JF4704" begin="0" fromJunction="J20" toJunction="J19" end="3600" vehsPerHour="18.32"/>
  <flow id="JF4705" begin="0" fromJunction="J20" toJunction="J21" end="3600" vehsPerHour="18.32"/>
  <flow id="JF4706" begin="0" fromJunction="J20" toJunction="J22" end="3600" vehsPerHour="18.32"/>
  <flow id="JF4707" begin="0" fromJunction="J20" toJunction="J7" end="3600" vehsPerHour="18.32"/>
  <flow id="JF4708" begin="0" fromJunction="J20" toJunction="J8" end="3600" vehsPerHour="18.32"/>
  <flow id="JF4709" begin="0" fromJunction="J20" toJunction="J9" end="3600" vehsPerHour="18.32"/>
  <flow id="JF4710" begin="0" fromJunction="J21" toJunction="J10" end="3600" vehsPerHour="18.32"/>
  <flow id="JF4711" begin="0" fromJunction="J21" toJunction="J11" end="3600" vehsPerHour="18.32"/>
  <flow id="JF4712" begin="0" fromJunction="J21" toJunction="J12" end="3600" vehsPerHour="18.32"/>
  <flow id="JF4713" begin="0" fromJunction="J21" toJunction="J13" end="3600" vehsPerHour="18.32"/>
  <flow id="JF4714" begin="0" fromJunction="J21" toJunction="J14" end="3600" vehsPerHour="18.32"/>
  <flow id="JF4715" begin="0" fromJunction="J21" toJunction="J15" end="3600" vehsPerHour="18.32"/>
  <flow id="JF4716" begin="0" fromJunction="J21" toJunction="J16" end="3600" vehsPerHour="18.32"/>
  <flow id="JF4717" begin="0" fromJunction="J21" toJunction="J17" end="3600" vehsPerHour="18.32"/>
  <flow id="JF4718" begin="0" fromJunction="J21" toJunction="J18" end="3600" vehsPerHour="18.32"/>
  <flow id="JF4719" begin="0" fromJunction="J21" toJunction="J19" end="3600" vehsPerHour="18.32"/>
  <flow id="JF4720" begin="0" fromJunction="J21" toJunction="J20" end="3600" vehsPerHour="18.32"/>
  <flow id="JF4721" begin="0" fromJunction="J21" toJunction="J22" end="3600" vehsPerHour="18.32"/>
  <flow id="JF4722" begin="0" fromJunction="J21" toJunction="J7" end="3600" vehsPerHour="18.32"/>
  <flow id="JF4723" begin="0" fromJunction="J21" toJunction="J8" end="3600" vehsPerHour="18.32"/>
  <flow id="JF4724" begin="0" fromJunction="J21" toJunction="J9" end="3600" vehsPerHour="18.32"/>
  <flow id="JF4725" begin="0" fromJunction="J22" toJunction="J10" end="3600" vehsPerHour="18.32"/>
  <flow id="JF4726" begin="0" fromJunction="J22" toJunction="J11" end="3600" vehsPerHour="18.32"/>
  <flow id="JF4727" begin="0" fromJunction="J22" toJunction="J12" end="3600" vehsPerHour="18.32"/>
  <flow id="JF4728" begin="0" fromJunction="J22" toJunction="J13" end="3600" vehsPerHour="18.32"/>
  <flow id="JF4729" begin="0" fromJunction="J22" toJunction="J14" end="3600" vehsPerHour="18.32"/>
  <flow id="JF4730" begin="0" fromJunction="J22" toJunction="J15" end="3600" vehsPerHour="18.32"/>
  <flow id="JF4731" begin="0" fromJunction="J22" toJunction="J16" end="3600" vehsPerHour="18.32"/>
  <flow id="JF4732" begin="0" fromJunction="J22" toJunction="J17" end="3600" vehsPerHour="18.32"/>
  <flow id="JF4733" begin="0" fromJunction="J22" toJunction="J18" end="3600" vehsPerHour="18.32"/>
  <flow id="JF4734" begin="0" fromJunction="J22" toJunction="J19" end="3600" vehsPerHour="18.32"/>
  <flow id="JF4735" begin="0" fromJunction="J22" toJunction="J20" end="3600" vehsPerHour="18.32"/>
  <flow id="JF4736" begin="0" fromJunction="J22" toJunction="J21" end="3600" vehsPerHour="18.32"/>
  <flow id="JF4737" begin="0" fromJunction="J22" toJunction="J7" end="3600" vehsPerHour="18.32"/>
  <flow id="JF4738" begin="0" fromJunction="J22" toJunction="J8" end="3600" vehsPerHour="18.32"/>
  <flow id="JF4739" begin="0" fromJunction="J22" toJunction="J9" end="3600" vehsPerHour="18.32"/>
  <flow id="JF4740" begin="0" fromJunction="J8" toJunction="J10" end="3600" vehsPerHour="36.64"/>
  <flow id="JF4741" begin="0" fromJunction="J8" toJunction="J11" end="3600" vehsPerHour="36.64"/>
  <flow id="JF4742" begin="0" fromJunction="J8" toJunction="J12" end="3600" vehsPerHour="36.64"/>
  <flow id="JF4743" begin="0" fromJunction="J8" toJunction="J13" end="3600" vehsPerHour="36.64"/>
  <flow id="JF4744" begin="0" fromJunction="J8" toJunction="J14" end="3600" vehsPerHour="36.64"/>
  <flow id="JF4745" begin="0" fromJunction="J8" toJunction="J15" end="3600" vehsPerHour="36.64"/>
  <flow id="JF4746" begin="0" fromJunction="J8" toJunction="J16" end="3600" vehsPerHour="36.64"/>
  <flow id="JF4747" begin="0" fromJunction="J8" toJunction="J17" end="3600" vehsPerHour="36.64"/>
  <flow id="JF4748" begin="0" fromJunction="J8" toJunction="J18" end="3600" vehsPerHour="36.64"/>
  <flow id="JF4749" begin="0" fromJunction="J8" toJunction="J19" end="3600" vehsPerHour="36.64"/>
  <flow id="JF4750" begin="0" fromJunction="J8" toJunction="J20" end="3600" vehsPerHour="36.64"/>
  <flow id="JF4751" begin="0" fromJunction="J8" toJunction="J21" end="3600" vehsPerHour="36.64"/>
  <flow id="JF4752" begin="0" fromJunction="J8" toJunction="J22" end="3600" vehsPerHour="36.64"/>
  <flow id="JF4753" begin="0" fromJunction="J8" toJunction="J7" end="3600" vehsPerHour="36.64"/>
  <flow id="JF4754" begin="0" fromJunction="J8" toJunction="J9" end="3600" vehsPerHour="36.64"/>
  <flow id="JF4755" begin="0" fromJunction="J9" toJunction="J10" end="3600" vehsPerHour="18.32"/>
  <flow id="JF4756" begin="0" fromJunction="J9" toJunction="J11" end="3600" vehsPerHour="18.32"/>
  <flow id="JF4757" begin="0" fromJunction="J9" toJunction="J12" end="3600" vehsPerHour="18.32"/>
  <flow id="JF4758" begin="0" fromJunction="J9" toJunction="J13" end="3600" vehsPerHour="18.32"/>
  <flow id="JF4759" begin="0" fromJunction="J9" toJunction="J14" end="3600" vehsPerHour="18.32"/>
  <flow id="JF4760" begin="0" fromJunction="J9" toJunction="J15" end="3600" vehsPerHour="18.32"/>
  <flow id="JF4761" begin="0" fromJunction="J9" toJunction="J16" end="3600" vehsPerHour="18.32"/>
  <flow id="JF4762" begin="0" fromJunction="J9" toJunction="J17" end="3600" vehsPerHour="18.32"/>
  <flow id="JF4763" begin="0" fromJunction="J9" toJunction="J18" end="3600" vehsPerHour="18.32"/>
  <flow id="JF4764" begin="0" fromJunction="J9" toJunction="J19" end="3600" vehsPerHour="18.32"/>
  <flow id="JF4765" begin="0" fromJunction="J9" toJunction="J20" end="3600" vehsPerHour="18.32"/>
  <flow id="JF4766" begin="0" fromJunction="J9" toJunction="J21" end="3600" vehsPerHour="18.32"/>
  <flow id="JF4767" begin="0" fromJunction="J9" toJunction="J22" end="3600" vehsPerHour="18.32"/>
  <flow id="JF4768" begin="0" fromJunction="J9" toJunction="J7" end="3600" vehsPerHour="18.32"/>
  <flow id="JF4769" begin="0" fromJunction="J9" toJunction="J8" end="3600" vehsPerHour="18.32"/>
  <flow id="JF4770" begin="0" fromJunction="J10" toJunction="J9" end="3600" vehsPerHour="18.32"/>
  <flow id="JF4771" begin="0" fromJunction="J10" toJunction="J8" end="3600" vehsPerHour="18.32"/>
  <flow id="JF4772" begin="0" fromJunction="J10" toJunction="J7" end="3600" vehsPerHour="18.32"/>
  <flow id="JF4773" begin="0" fromJunction="J10" toJunction="J22" end="3600" vehsPerHour="18.32"/>
  <flow id="JF4774" begin="0" fromJunction="J10" toJunction="J21" end="3600" vehsPerHour="18.32"/>
  <flow id="JF4775" begin="0" fromJunction="J10" toJunction="J20" end="3600" vehsPerHour="18.32"/>
  <flow id="JF4776" begin="0" fromJunction="J10" toJunction="J19" end="3600" vehsPerHour="18.32"/>
  <flow id="JF4777" begin="0" fromJunction="J10" toJunction="J18" end="3600" vehsPerHour="18.32"/>
  <flow id="JF4778" begin="0" fromJunction="J10" toJunction="J17" end="3600" vehsPerHour="18.32"/>
  <flow id="JF4779" begin="0" fromJunction="J10" toJunction="J16" end="3600" vehsPerHour="18.32"/>
  <flow id="JF4780" begin="0" fromJunction="J10" toJunction="J15" end="3600" vehsPerHour="18.32"/>
  <flow id="JF4781" begin="0" fromJunction="J10" toJunction="J14" end="3600" vehsPerHour="18.32"/>
  <flow id="JF4782" begin="0" fromJunction="J10" toJunction="J13" end="3600" vehsPerHour="18.32"/>
  <flow id="JF4783" begin="0" fromJunction="J10" toJunction="J12" end="3600" vehsPerHour="18.32"/>
  <flow id="JF4784" begin="0" fromJunction="J10" toJunction="J11" end="3600" vehsPerHour="18.32"/>
  <flow id="JF4785" begin="0" fromJunction="J7" toJunction="J10" end="3600" vehsPerHour="36.64"/>
  <flow id="JF4786" begin="0" fromJunction="J7" toJunction="J11" end="3600" vehsPerHour="36.64"/>
  <flow id="JF4787" begin="0" fromJunction="J7" toJunction="J12" end="3600" vehsPerHour="36.64"/>
  <flow id="JF4788" begin="0" fromJunction="J7" toJunction="J13" end="3600" vehsPerHour="36.64"/>
  <flow id="JF4789" begin="0" fromJunction="J7" toJunction="J14" end="3600" vehsPerHour="36.64"/>
  <flow id="JF4790" begin="0" fromJunction="J7" toJunction="J15" end="3600" vehsPerHour="36.64"/>
  <flow id="JF4791" begin="0" fromJunction="J7" toJunction="J16" end="3600" vehsPerHour="36.64"/>
  <flow id="JF4792" begin="0" fromJunction="J7" toJunction="J17" end="3600" vehsPerHour="36.64"/>
  <flow id="JF4793" begin="0" fromJunction="J7" toJunction="J18" end="3600" vehsPerHour="36.64"/>
  <flow id="JF4794" begin="0" fromJunction="J7" toJunction="J19" end="3600" vehsPerHour="36.64"/>
  <flow id="JF4795" begin="0" fromJunction="J7" toJunction="J20" end="3600" vehsPerHour="36.64"/>
  <flow id="JF4796" begin="0" fromJunction="J7" toJunction="J21" end="3600" vehsPerHour="36.64"/>
  <flow id="JF4797" begin="0" fromJunction="J7" toJunction="J22" end="3600" vehsPerHour="36.64"/>
  <flow id="JF4798" begin="0" fromJunction="J7" toJunction="J8" end="3600" vehsPerHour="36.64"/>
  <flow id="JF4799" begin="0" fromJunction="J7" toJunction="J9" end="3600" vehsPerHour="36.64"/>
</routes>